MANIFEST.in
README.md
requirements.txt
setup.py
django_power_cms/__init__.py
django_power_cms/admin.py
django_power_cms/apps.py
django_power_cms/export_templates.py
django_power_cms/export_themes.py
django_power_cms/models.py
django_power_cms/settings.py
django_power_cms/tests.py
django_power_cms/urls.py
django_power_cms/views.py
django_power_cms.egg-info/PKG-INFO
django_power_cms.egg-info/SOURCES.txt
django_power_cms.egg-info/dependency_links.txt
django_power_cms.egg-info/not-zip-safe
django_power_cms.egg-info/requires.txt
django_power_cms.egg-info/top_level.txt
django_power_cms/locale/zh_Hans/LC_MESSAGES/django.mo
django_power_cms/locale/zh_Hans/LC_MESSAGES/django.po
django_power_cms/management/__init__.py
django_power_cms/management/commands/django-power-cms-template.py
django_power_cms/management/commands/django-power-cms-theme.py
django_power_cms/migrations/0001_initial.py
django_power_cms/migrations/0002_auto_20200305_1559.py
django_power_cms/migrations/0003_template_code.py
django_power_cms/migrations/0004_auto_20200305_1848.py
django_power_cms/migrations/0005_auto_20200305_2136.py
django_power_cms/migrations/0006_auto_20200307_2148.py
django_power_cms/migrations/0007_auto_20200308_2114.py
django_power_cms/migrations/0008_auto_20200308_2150.py
django_power_cms/migrations/0009_articledetailwidget_show_description.py
django_power_cms/migrations/0010_auto_20200308_2206.py
django_power_cms/migrations/0011_auto_20200309_1735.py
django_power_cms/migrations/0012_auto_20200309_2121.py
django_power_cms/migrations/0013_auto_20200319_1039.py
django_power_cms/migrations/0014_site_favicon.py
django_power_cms/migrations/0015_article_site.py
django_power_cms/migrations/0016_auto_20200321_1726.py
django_power_cms/migrations/0017_auto_20200321_1838.py
django_power_cms/migrations/0018_auto_20200322_1010.py
django_power_cms/migrations/0019_auto_20200322_1012.py
django_power_cms/migrations/0020_auto_20200322_2234.py
django_power_cms/migrations/0021_cardsitem_cardswidget.py
django_power_cms/migrations/0022_auto_20200323_0907.py
django_power_cms/migrations/0023_auto_20200323_1020.py
django_power_cms/migrations/0024_auto_20200323_1201.py
django_power_cms/migrations/__init__.py
